imprint/__init__.py
imprint/driver.py
imprint/version.py
imprint/core/__init__.py
imprint/core/defaults.py
imprint/core/parsers.py
imprint/core/state.py
imprint/core/tags.py
imprint/core/utilities.py
imprint/handlers/__init__.py
imprint/handlers/utilities.py
imprint/handlers/figure/__init__.py
imprint/handlers/figure/images.py
imprint/handlers/string/__init__.py
imprint/handlers/string/strings.py
imprint/handlers/table/__init__.py
imprint/handlers/table/tables.py
imprint-0.1a1.dev1.data/data/LICENSE
imprint-0.1a1.dev1.data/data/README
imprint-0.1a1.dev1.data/scripts/docx2xml
imprint-0.1a1.dev1.data/scripts/imprint
imprint-0.1a1.dev1.dist-info/LICENSE
imprint-0.1a1.dev1.dist-info/METADATA
imprint-0.1a1.dev1.dist-info/WHEEL
imprint-0.1a1.dev1.dist-info/top_level.txt
imprint-0.1a1.dev1.dist-info/RECORD
