Metadata-Version: 2.1
Name: imprint
Version: 0.1a1.dev1
Summary: Program for creating MS Word reports from data and content templates
Home-page: https://github.com/madphysicist/imprint
Author: Joseph R. Fox-Rabinovitz
Author-email: jfoxrabinovitz@gmail.com
Maintainer: Joseph R. Fox-Rabinovitz
Maintainer-email: jfoxrabinovitz@gmail.com
License: GNU Affero General Public License v3 or later (AGPLv3+)
Project-URL: Bugs, https://github.com/madphysicist/imprint/issues
Project-URL: Documentation, https://imprint.readthedocs.io/en/latest/
Platform: UNKNOWN
Classifier: Development Status :: 2 - Pre-Alpha
Classifier: Intended Audience :: Financial and Insurance Industry
Classifier: Intended Audience :: Healthcare Industry
Classifier: Intended Audience :: Legal Industry
Classifier: Intended Audience :: Manufacturing
Classifier: Intended Audience :: Science/Research
Classifier: Intended Audience :: Other Audience
Classifier: License :: OSI Approved :: GNU Affero General Public License v3 or later (AGPLv3+)
Classifier: Operating System :: Microsoft :: Windows
Classifier: Operating System :: POSIX :: Linux
Classifier: Operating System :: Unix
Classifier: Programming Language :: Python
Classifier: Programming Language :: Python :: 3 :: Only
Classifier: Programming Language :: Python :: 3.6
Classifier: Programming Language :: Python :: 3.7
Classifier: Programming Language :: Python :: 3.8
Classifier: Topic :: Office/Business
Classifier: Topic :: Text Processing :: Markup :: XML
Classifier: Topic :: Utilities
Provides: imprint
Requires-Dist: python-docx (>=0.8.5)
Requires-Dist: haggis[docx] (>=0.1a1.dev1)
Provides-Extra: all
Requires-Dist: pandas (>=0.20) ; extra == 'all'
Requires-Dist: haggis[latex,pdf] (>=0.1a1.dev1) ; extra == 'all'
Provides-Extra: docs
Requires-Dist: sphinx (>=1.7.1) ; extra == 'docs'
Provides-Extra: docs-rtd
Requires-Dist: sphinx (>=1.7.1) ; extra == 'docs-rtd'
Requires-Dist: sphinx-rtd-theme (>=0.4.0) ; extra == 'docs-rtd'
Provides-Extra: latex
Requires-Dist: haggis[latex] (>=0.1a1.dev1) ; extra == 'latex'
Provides-Extra: pdf
Requires-Dist: haggis[pdf] (>=0.1a1.dev1) ; extra == 'pdf'
